xkpassgen/__init__.py
xkpassgen/xkpassgen.py
xkpassgen/lib/__init__.py
xkpassgen/lib/case.py
xkpassgen/static/.gitignore
xkpassgen/static/eff-long
xkpassgen/static/eff-short
xkpassgen/static/eff-special
xkpassgen/static/test_list
xkpassgen/static/test_files/stdin_main_interactive
xkpassgen-1.0.5.dist-info/LICENSE
xkpassgen-1.0.5.dist-info/LICENSE.BSD
xkpassgen-1.0.5.dist-info/METADATA
xkpassgen-1.0.5.dist-info/WHEEL
xkpassgen-1.0.5.dist-info/entry_points.txt
xkpassgen-1.0.5.dist-info/top_level.txt
xkpassgen-1.0.5.dist-info/RECORD
