Metadata-Version: 2.1
Name: xkpassgen
Version: 1.0.5
Summary: Generate secure multiword passwords/passphrases, inspired by XKCD
Home-page: https://github.com/adambirds/xkcd-password-gen
Author: Adam Birds
Author-email: adam.birds@adbwebdesigns.co.uk
License: LGPLv3
Project-URL: Bug Tracker, https://github.com/adambirds/xkcd-password-gen/issues
Platform: UNKNOWN
Classifier: License :: OSI Approved :: GNU General Public License v3 (GPLv3)
Classifier: Programming Language :: Python :: 3
Classifier: Operating System :: OS Independent
Requires-Python: >=3.6
